{
  "place_of_publication": "Springfield, Ill.", 
  "lccn": "2012254021", 
  "start_year": "1920", 
  "place": [
    "Illinois--Sangamon--Springfield"
  ], 
  "name": "The Illinois conservator. [online resource]", 
  "publisher": "E.L. Rogers", 
  "url": "http://chroniclingamerica.loc.gov/lccn/2012254021.json", 
  "end_year": "19??", 
  "issues": [], 
  "subject": [
    "African American newspapers--Illinois--Springfield.", 
    "African American newspapers.--fast--(OCoLC)fst00799278", 
    "African Americans--Illinois--Springfield--Newspapers.", 
    "African Americans.--fast--(OCoLC)fst00799558", 
    "Illinois--Springfield.--fast--(OCoLC)fst01204937", 
    "Springfield (Ill.)--Newspapers."
  ]
}