{
  "place_of_publication": "Evanston, Ill.", 
  "lccn": "sn00062055", 
  "start_year": "2000", 
  "place": [
    "Illinois--Cook--Evanston"
  ], 
  "name": "Evanston sentinel.", 
  "publisher": "Walter A. Perkins, III", 
  "url": "http://chroniclingamerica.loc.gov/lccn/sn00062055.json", 
  "end_year": "current", 
  "issues": [], 
  "subject": [
    "African Americans--Illinois--Newspapers.", 
    "African Americans.--fast--(OCoLC)fst00799558", 
    "Evanston (Ill.)--Newspapers.", 
    "Illinois--Evanston.--fast--(OCoLC)fst01204903", 
    "Illinois.--fast--(OCoLC)fst01205143"
  ]
}