{
  "place_of_publication": "Rockford [Ill.]", 
  "lccn": "sn82015928", 
  "start_year": "1950", 
  "place": [
    "Illinois--Winnebago--Rockford"
  ], 
  "name": "The crusader.", 
  "publisher": "Crusader Pub. Co.", 
  "url": "http://chroniclingamerica.loc.gov/lccn/sn82015928.json", 
  "end_year": "19??", 
  "issues": [], 
  "subject": [
    "African Americans--Illinois--Freeport--Newspapers.", 
    "African Americans--Illinois--Rockford--Newspapers.", 
    "African Americans--Wisconsin--Beloit--Newspapers.", 
    "African Americans.--fast--(OCoLC)fst00799558", 
    "Beloit (Wis.)--Newspapers.", 
    "Freeport (Ill.)--Newspapers.", 
    "Illinois--Freeport.--fast--(OCoLC)fst01217738", 
    "Illinois--Rockford.--fast--(OCoLC)fst01208839", 
    "Rockford (Ill.)--Newspapers.", 
    "Wisconsin--Beloit.--fast--(OCoLC)fst01222348"
  ]
}