{
  "place_of_publication": "Bloomington, Ill.", 
  "lccn": "sn90054689", 
  "start_year": "1972", 
  "place": [
    "Illinois--McLean--Bloomington", 
    "Illinois--McLean--Decatur", 
    "Illinois--McLean--Normal", 
    "Illinois--McLean--Peoria", 
    "Illinois--McLean--Springfield"
  ], 
  "name": "The voice of the Black community.", 
  "publisher": "[publisher not identified]", 
  "url": "http://chroniclingamerica.loc.gov/lccn/sn90054689.json", 
  "end_year": "199?", 
  "issues": [], 
  "subject": [
    "African American newspapers--fast--(OCoLC)fst00799278", 
    "African American newspapers--Illinois--Bloomington.", 
    "African American newspapers--Illinois--Normal.", 
    "African Americans--Illinois--Bloomington--Newspapers.", 
    "African Americans--Illinois--Normal--Newspapers.", 
    "African Americans.--fast--(OCoLC)fst00799558", 
    "Bloomington (Ill.)--Newspapers.", 
    "Illinois--Bloomington.--fast--(OCoLC)fst01205022", 
    "Illinois--Normal.--fast--(OCoLC)fst01208903", 
    "Normal (Ill.)--Newspapers."
  ]
}